livechess/__init__.py
livechess/__main__.py
livechess/local.py
livechess/main.py
livechess-0.1.0.dist-info/METADATA
livechess-0.1.0.dist-info/WHEEL
livechess-0.1.0.dist-info/entry_points.txt
livechess-0.1.0.dist-info/RECORD
