Metadata-Version: 2.1
Name: livechess
Version: 0.1.0
Summary: Command line utility to assist liveboard operators
Author: Sernin van de Krol
Author-email: serninpc@paneidos.net
Requires-Python: >=3.12,<4.0
Classifier: Programming Language :: Python :: 3
Classifier: Programming Language :: Python :: 3.12
Requires-Dist: chess (>=1.10.0,<2.0.0)
Requires-Dist: more-itertools (>=10.4.0,<11.0.0)
Requires-Dist: requests (>=2.32.3,<3.0.0)
Requires-Dist: typer[all] (>=0.12.5,<0.13.0)
